<?xml version="1.0" encoding="UTF-8"?>
<objects serializationModel="Studio.02.02.00">
	<object class="AudioFile" id="{44d973ad-cadb-4ff3-ac1d-c710e088a452}">
		<property name="assetPath">
			<value>368710__rhinctus__mystical-music.mp3</value>
		</property>
		<property name="isStreaming">
			<value>true</value>
		</property>
		<property name="frequencyInKHz">
			<value>44.0999985</value>
		</property>
		<property name="channelCount">
			<value>2</value>
		</property>
		<property name="length">
			<value>71.392653061224493</value>
		</property>
		<relationship name="masterAssetFolder">
			<destination>{d588ff38-f2f6-4330-a524-6c907a8192e4}</destination>
		</relationship>
	</object>
</objects>
